LICENSE
MANIFEST.in
README
setup.py
tasky/__init__.py
tasky/config.py
tasky/loop.py
tasky/stats.py
tasky.egg-info/PKG-INFO
tasky.egg-info/SOURCES.txt
tasky.egg-info/dependency_links.txt
tasky.egg-info/top_level.txt
tasky/tasks/__init__.py
tasky/tasks/periodic.py
tasky/tasks/queue.py
tasky/tasks/task.py
tasky/tasks/timer.py