Metadata-Version: 1.1
Name: tasky
Version: 0.7.2
Summary: asyncio framework for task-based execution
Home-page: https://github.com/jreese/tasky
Author: John Reese
Author-email: john@noswap.com
License: MIT License
Platform: UNKNOWN
Classifier: License :: OSI Approved :: MIT License
Classifier: Operating System :: OS Independent
Classifier: Programming Language :: Python
Classifier: Programming Language :: Python :: 3.5
Classifier: Topic :: Utilities
Classifier: Development Status :: 4 - Beta
